emulsion/__init__.py
emulsion/__main__.py
emulsion/init_emulsion.py
emulsion/agent/__init__.py
emulsion/agent/action.py
emulsion/agent/atoms.py
emulsion/agent/comparts.py
emulsion/agent/exceptions.py
emulsion/agent/meta.py
emulsion/agent/process.py
emulsion/agent/views.py
emulsion/agent/core/__init__.py
emulsion/agent/core/abstract_agent.py
emulsion/agent/core/emulsion_agent.py
emulsion/agent/core/groups.py
emulsion/agent/managers/__init__.py
emulsion/agent/managers/abstract_process_manager.py
emulsion/agent/managers/compart_process_manager.py
emulsion/agent/managers/functions.py
emulsion/agent/managers/group_manager.py
emulsion/agent/managers/ibm_process_manager.py
emulsion/agent/managers/metapop_process_manager.py
emulsion/agent/managers/multi_process_manager.py
emulsion/model/__init__.py
emulsion/model/emulsion_model.py
emulsion/model/exceptions.py
emulsion/model/functions.py
emulsion/model/state_machines.py
emulsion/resources/emulsion.tx
emulsion/scripts/emulsion-completion.sh
emulsion/tools/__init__.py
emulsion/tools/calendar.py
emulsion/tools/functions.py
emulsion/tools/getters.py
emulsion/tools/graph.py
emulsion/tools/misc.py
emulsion/tools/parallel.py
emulsion/tools/plot.py
emulsion/tools/simulation.py
emulsion/tools/state.py
emulsion/tools/timing.py
emulsion/tools/view.py
emulsion-1.1.1.dist-info/LICENSE
emulsion-1.1.1.dist-info/METADATA
emulsion-1.1.1.dist-info/NOTICE
emulsion-1.1.1.dist-info/WHEEL
emulsion-1.1.1.dist-info/entry_points.txt
emulsion-1.1.1.dist-info/top_level.txt
emulsion-1.1.1.dist-info/RECORD
